finetune_eval_harness/__init__.py
finetune_eval_harness/main.py
finetune_eval_harness/process_args.py
finetune_eval_harness/hf_scripts/__init__.py
finetune_eval_harness/hf_scripts/data_trainining_args.py
finetune_eval_harness/hf_scripts/hgf_fine_tune_class.py
finetune_eval_harness/hf_scripts/hgf_fine_tune_ner.py
finetune_eval_harness/hf_scripts/hgf_fine_tune_qa.py
finetune_eval_harness/hf_scripts/initial_arguments.py
finetune_eval_harness/hf_scripts/model_args.py
finetune_eval_harness/hf_scripts/trainer.py
finetune_eval_harness/hf_scripts/trainer_qa.py
finetune_eval_harness/hf_scripts/utility_functions.py
finetune_eval_harness/hf_scripts/utils_qa.py
finetune_eval_harness/tasks/__init__.py
finetune_eval_harness/tasks/bulgarian_sentiment.py
finetune_eval_harness/tasks/classification.py
finetune_eval_harness/tasks/croatian_sentiment.py
finetune_eval_harness/tasks/czech_subjectivity.py
finetune_eval_harness/tasks/danish_misogyny.py
finetune_eval_harness/tasks/dutch_social.py
finetune_eval_harness/tasks/ehealth_kd.py
finetune_eval_harness/tasks/eur_lux.py
finetune_eval_harness/tasks/finish_sentiment.py
finetune_eval_harness/tasks/flue.py
finetune_eval_harness/tasks/german_europarl.py
finetune_eval_harness/tasks/german_ner.py
finetune_eval_harness/tasks/german_quad.py
finetune_eval_harness/tasks/germeval2017.py
finetune_eval_harness/tasks/germeval2018.py
finetune_eval_harness/tasks/gnad10.py
finetune_eval_harness/tasks/greek_legal.py
finetune_eval_harness/tasks/klej_dyk.py
finetune_eval_harness/tasks/maltese_sentiment.py
finetune_eval_harness/tasks/mapa.py
finetune_eval_harness/tasks/ner.py
finetune_eval_harness/tasks/pawsx.py
finetune_eval_harness/tasks/piaf.py
finetune_eval_harness/tasks/polish_dyk.py
finetune_eval_harness/tasks/qa.py
finetune_eval_harness/tasks/rucola.py
finetune_eval_harness/tasks/slovak_sentiment.py
finetune_eval_harness/tasks/spanish_conll.py
finetune_eval_harness/tasks/spanish_ehealth.py
finetune_eval_harness/tasks/spanish_quad.py
finetune_eval_harness-0.6.12.dev1.dist-info/LICENSE
finetune_eval_harness-0.6.12.dev1.dist-info/METADATA
finetune_eval_harness-0.6.12.dev1.dist-info/WHEEL
finetune_eval_harness-0.6.12.dev1.dist-info/dependency_links.txt
finetune_eval_harness-0.6.12.dev1.dist-info/entry_points.txt
finetune_eval_harness-0.6.12.dev1.dist-info/top_level.txt
finetune_eval_harness-0.6.12.dev1.dist-info/RECORD
